deutschland/vag/__init__.py
deutschland/vag/api/__init__.py
deutschland/vag/api/abfahrten_api.py
deutschland/vag/api/fahrten_api.py
deutschland/vag/api/haltestellen_api.py
deutschland/vag/api_client.py
deutschland/vag/apis/__init__.py
deutschland/vag/configuration.py
deutschland/vag/exceptions.py
deutschland/vag/model/__init__.py
deutschland/vag/model/abfahrt_dto.py
deutschland/vag/model/abfahrten_api_response.py
deutschland/vag/model/fahrt_dto.py
deutschland/vag/model/fahrten_api_response.py
deutschland/vag/model/fahrweg_halteposition_dto.py
deutschland/vag/model/haltestelle_dto.py
deutschland/vag/model/haltestellen_api_response.py
deutschland/vag/model/metadata.py
deutschland/vag/model_utils.py
deutschland/vag/models/__init__.py
deutschland/vag/rest.py
de_vag-0.1.0.dist-info/WHEEL
de_vag-0.1.0.dist-info/METADATA
de_vag-0.1.0.dist-info/RECORD
